odoo9_addon_printer_zpl2-9.0.1.0.0-py2.7-nspkg.pth
odoo9_addon_printer_zpl2-9.0.1.0.0.dist-info/top_level.txt
odoo9_addon_printer_zpl2-9.0.1.0.0.dist-info/WHEEL
odoo9_addon_printer_zpl2-9.0.1.0.0.dist-info/RECORD
odoo9_addon_printer_zpl2-9.0.1.0.0.dist-info/metadata.json
odoo9_addon_printer_zpl2-9.0.1.0.0.dist-info/DESCRIPTION.rst
odoo9_addon_printer_zpl2-9.0.1.0.0.dist-info/METADATA
odoo9_addon_printer_zpl2-9.0.1.0.0.dist-info/namespace_packages.txt
odoo_addons/printer_zpl2/__openerp__.py
odoo_addons/printer_zpl2/__init__.py
odoo_addons/printer_zpl2/README.rst
odoo_addons/printer_zpl2/security/ir.model.access.csv
odoo_addons/printer_zpl2/models/printing_label_zpl2_component.py
odoo_addons/printer_zpl2/models/printing_label_zpl2.py
odoo_addons/printer_zpl2/models/__init__.py
odoo_addons/printer_zpl2/wizard/print_record_label.py
odoo_addons/printer_zpl2/wizard/print_record_label.xml
odoo_addons/printer_zpl2/wizard/__init__.py
odoo_addons/printer_zpl2/views/printing_label_zpl2.xml
odoo_addons/printer_zpl2/tests/test_wizard_print_record_label.py
odoo_addons/printer_zpl2/tests/__init__.py
odoo_addons/printer_zpl2/tests/test_printing_label_zpl2.py
